lab_control/__init__.py
lab_control/common.py
lab_control/dsox2024a.py
lab_control/e5061b.py
lab_control/n90X0x.py
lab_control/rpc.py
lab_control/sr785.py
lab_control/stepper_board.py
lab_control-0.10.0.dist-info/METADATA
lab_control-0.10.0.dist-info/WHEEL
lab_control-0.10.0.dist-info/RECORD
