Metadata-Version: 2.1
Name: lab-control
Version: 0.10.0
Summary: Remote control lab instruments
Author: Lorenz Kies
Author-email: lorenz.kies@aei.mpg.de
Requires-Python: >=3.11,<4.0
Classifier: Programming Language :: Python :: 3
Classifier: Programming Language :: Python :: 3.11
Classifier: Programming Language :: Python :: 3.12
Classifier: Programming Language :: Python :: 3.13
Requires-Dist: numpy
Requires-Dist: pandas
Requires-Dist: plotly
Requires-Dist: pyserial (>=3.5,<4.0)
Requires-Dist: pyvisa
Requires-Dist: pyyaml (>=6.0.2,<7.0.0)
